tgback/__init__.py
tgback/app.py
tgback/tools.py
tgback/version.py
tgback/data/help.txt
tgback-5.2.1.dist-info/LICENSE
tgback-5.2.1.dist-info/METADATA
tgback-5.2.1.dist-info/WHEEL
tgback-5.2.1.dist-info/entry_points.txt
tgback-5.2.1.dist-info/top_level.txt
tgback-5.2.1.dist-info/RECORD
