Metadata-Version: 2.1
Name: tgback
Version: 5.2.1
Summary: tgback — a program for backing and restoring Telegram accounts
Home-page: https://github.com/NotStatilko/tgback
Download-URL: https://github.com/NotStatilko/tgback/archive/refs/tags/v5.2.1.tar.gz
Author-email: thenonproton@pm.me
License: MIT
Keywords: Telegram,Backup,CLI,Account,Non-official
License-File: LICENSE
Requires-Dist: pyaes (==1.6.1)
Requires-Dist: telethon (==1.36.0)
Provides-Extra: qr
Requires-Dist: pillow ; extra == 'qr'
Requires-Dist: pyzbar (==0.1.8) ; extra == 'qr'
Requires-Dist: qrcode (==6.1) ; extra == 'qr'
